monorepo_factory/__main__.py
monorepo_factory-1.0.1.dist-info/LICENSE
monorepo_factory-1.0.1.dist-info/METADATA
monorepo_factory-1.0.1.dist-info/WHEEL
monorepo_factory-1.0.1.dist-info/RECORD
